pycidr/__init__.py
pycidr/cli.py
pycidr/display.py
pycidr/ipv4/__init__.py
pycidr/ipv4/ipv4.py
pycidr/ipv4/ipv4_mask.py
pycidr/ipv4/ipv4_network.py
pycidr-0.1.1.dist-info/LICENSE
pycidr-0.1.1.dist-info/METADATA
pycidr-0.1.1.dist-info/WHEEL
pycidr-0.1.1.dist-info/entry_points.txt
pycidr-0.1.1.dist-info/RECORD
