Metadata-Version: 2.1
Name: pycidr
Version: 0.1.1
Summary: A simple IP subnetting calculator
Author: jmillana
Author-email: jordi@marimon.tech
Requires-Python: >=3.10,<4.0
Classifier: Programming Language :: Python :: 3
Classifier: Programming Language :: Python :: 3.10
Classifier: Programming Language :: Python :: 3.11
Requires-Dist: rich (>=13.3.4,<14.0.0)
Requires-Dist: typer (>=0.7.0,<0.8.0)
Requires-Dist: typer-cloup (>=0.11.0,<0.12.0)
